slice.py
audio_slice-0.0.6.2.dist-info/LICENSE.md
audio_slice-0.0.6.2.dist-info/METADATA
audio_slice-0.0.6.2.dist-info/WHEEL
audio_slice-0.0.6.2.dist-info/entry_points.txt
audio_slice-0.0.6.2.dist-info/top_level.txt
audio_slice-0.0.6.2.dist-info/RECORD
