Metadata-Version: 2.1
Name: audio-slice
Version: 0.0.6.2
Summary: A command line utility to slice MP3 files into pieces.
Home-page: https://github.com/shebanginc/audio-slice
Author: Kurt Collins
Author-email: kurt@kurt.sx
License: UNKNOWN
Platform: UNKNOWN
Classifier: Development Status :: 2 - Pre-Alpha
Classifier: Environment :: Console
Classifier: License :: OSI Approved :: MIT License
Classifier: Operating System :: OS Independent
Classifier: Programming Language :: Python :: 2.7
Classifier: Programming Language :: Python :: 3
Requires-Dist: Click
Requires-Dist: pydub
